<?xml version="1.0" encoding="utf-8"?>
<ImportExportXml xmlns:xsi="http://www.w3.org/2001/XMLSchema-instance" OrganizationVersion="9.2.25013.146" OrganizationSchemaType="Standard" CRMServerServiceabilityVersion="9.2.25014.00158">
  <Entities />
  <Roles />
  <Workflows />
  <FieldSecurityProfiles />
  <Templates />
  <EntityMaps />
  <EntityRelationships />
  <OrganizationSettings />
  <optionsets />
  <CustomControls />
  <EntityDataProviders />
  <AppModuleSiteMaps />
  <AppModules />
  <connectionreferences>
    <connectionreference connectionreferencelogicalname="udpp25_sharedcommondataserviceforapps_85a1a">
      <connectionreferencedisplayname>udpp25_sharedcommondataserviceforapps_85a1a</connectionreferencedisplayname>
      <connectorid>/providers/Microsoft.PowerApps/apis/shared_commondataserviceforapps</connectorid>
      <iscustomizable>1</iscustomizable>
      <promptingbehavior>0</promptingbehavior>
      <statecode>0</statecode>
      <statuscode>1</statuscode>
    </connectionreference>
    <connectionreference connectionreferencelogicalname="udpp25_shareddataflows_efc61">
      <connectionreferencedisplayname>udpp25_shareddataflows_efc61</connectionreferencedisplayname>
      <connectorid>/providers/Microsoft.PowerApps/apis/shared_dataflows</connectorid>
      <iscustomizable>1</iscustomizable>
      <promptingbehavior>0</promptingbehavior>
      <statecode>0</statecode>
      <statuscode>1</statuscode>
    </connectionreference>
  </connectionreferences>
  <msdyn_dataflows>
    <msdyn_dataflow msdyn_dataflowid="a0186ab3-f3e2-ef11-9342-00224883c250">
      <iscustomizable>1</iscustomizable>
      <msdyn_internalversion>e634101d-e763-4c8a-9782-a11487a894b7</msdyn_internalversion>
      <msdyn_mashupdocument>section Section1;
shared _baseUrl = let
  _baseUrl = "https://pokeapi.co/api/v2/"
in
  _baseUrl;
shared #"e_pokemons-api" = let
  Source = Json.Document(Web.Contents(_baseUrl &amp; "pokemon")),
  #"Converted to table" = Table.FromRecords({Source}),
  #"Expanded results" = Table.ExpandListColumn(#"Converted to table", "results"),
  #"Expanded results1" = Table.ExpandRecordColumn(#"Expanded results", "results", {"name", "url"}, {"results.name", "results.url"}),
  #"Changed column type" = Table.TransformColumnTypes(#"Expanded results1", {{"count", Int64.Type}, {"next", type text}, {"results.name", type text}, {"results.url", type text}})
in
  #"Changed column type";
shared udpp25_pokemon = let
  Source = Table.FromRecords({}),
  #"Appended query" = Table.Combine({Source, #"t_pokemons-api"})
in
  #"Appended query";
shared #"t_pokemons-api" = let
  Source = #"e_pokemons-api",
  #"Choose columns" = Table.SelectColumns(Source, {"results.name", "results.url"}),
  #"Renamed columns" = Table.RenameColumns(#"Choose columns", {{"results.name", "udpp25_Name"}, {"results.url", "udpp25_Url"}})
in
  #"Renamed columns";
</msdyn_mashupdocument>
      <msdyn_mashupsettings>{"QueryGroups":[{"Id":"41902d4e-14d9-423c-bfd9-a3c05086e3a3","Name":"extract","Description":"","ParentId":null,"Order":0},{"Id":"c899add4-255b-4c9a-9d48-d233b6029e26","Name":"pokemon-api","Description":"","ParentId":"41902d4e-14d9-423c-bfd9-a3c05086e3a3","Order":0},{"Id":"19ec7a85-154a-489e-a191-2ee90d018aa2","Name":"transform","Description":"","ParentId":null,"Order":1},{"Id":"d7ddedf8-c3d5-4d9c-b2c0-06f0c6f96ee5","Name":"load","Description":"","ParentId":null,"Order":2}],"DocumentLocale":"en-US","QueriesMetadata":{"_baseUrl":{"QueryId":"5b28a664-9c1d-46af-b60c-9743b529d218","QueryName":"_baseUrl","QueryGroupId":"c899add4-255b-4c9a-9d48-d233b6029e26","EntityName":null,"LastKnownIsCalculatedEntity":false,"LastKnownIsLinkedEntity":false,"LastKnownIsParameter":false,"IsHidden":null,"LastKnownResultTypeName":"text","LoadEnabled":false,"DeleteExistingDataOnLoad":false,"FieldsMetadata":{},"HostProperties":{"MappingEditorProperties":"{}","ServiceFeatureFlag_EnableNewCdstDataflowOrchestration":"True","CdsUploadExecutorKey":"CdsUploader","ServiceFeatureFlag_EnableDataflowImported":"True","StorageId":"CD000000-0000-0000-0000-0000000000CD","EnvironmentId":null},"JsonOutputDestinations":null,"BindToDefaultOutputDestination":null,"JsonIncrementalRefreshSettings":null,"JsonStagingDefinition":null},"e_pokemons-api":{"QueryId":"0fb86dd5-096e-4a2f-9814-61b6b6048368","QueryName":"e_pokemons-api","QueryGroupId":"c899add4-255b-4c9a-9d48-d233b6029e26","EntityName":null,"LastKnownIsCalculatedEntity":false,"LastKnownIsLinkedEntity":false,"LastKnownIsParameter":false,"IsHidden":null,"LastKnownResultTypeName":"table","LoadEnabled":false,"DeleteExistingDataOnLoad":false,"FieldsMetadata":{},"HostProperties":{"MappingEditorProperties":"{}","ServiceFeatureFlag_EnableNewCdstDataflowOrchestration":"True","CdsUploadExecutorKey":"CdsUploader","ServiceFeatureFlag_EnableDataflowImported":"True","StorageId":"CD000000-0000-0000-0000-0000000000CD","EnvironmentId":null},"JsonOutputDestinations":null,"BindToDefaultOutputDestination":null,"JsonIncrementalRefreshSettings":null,"JsonStagingDefinition":null},"udpp25_pokemon":{"QueryId":"44a4bf99-c8bd-430a-af85-a60a23e41c06","QueryName":"udpp25_pokemon","QueryGroupId":"d7ddedf8-c3d5-4d9c-b2c0-06f0c6f96ee5","EntityName":"udpp25_Pokemon","LastKnownIsCalculatedEntity":false,"LastKnownIsLinkedEntity":false,"LastKnownIsParameter":false,"IsHidden":null,"LastKnownResultTypeName":"table","LoadEnabled":true,"DeleteExistingDataOnLoad":true,"FieldsMetadata":{"udpp25_Name":{"SourceColumnName":"udpp25_Name","DestinationFieldType":"Memo","AutoNumberSettings":null},"udpp25_Url":{"SourceColumnName":"udpp25_Url","DestinationFieldType":"Memo","AutoNumberSettings":null}},"HostProperties":{"MappingEditorProperties":"{\"primaryKeyLogicalName\":\"udpp25_name\"}","ServiceFeatureFlag_EnableNewCdstDataflowOrchestration":"True","CdsUploadExecutorKey":"CdsUploader","ServiceFeatureFlag_EnableDataflowImported":"True","StorageId":"CD000000-0000-0000-0000-0000000000CD","EnvironmentId":null},"JsonOutputDestinations":null,"BindToDefaultOutputDestination":null,"JsonIncrementalRefreshSettings":null,"JsonStagingDefinition":null},"t_pokemons-api":{"QueryId":"ef1c7404-79d6-4d51-9940-e1d32b7011fe","QueryName":"t_pokemons-api","QueryGroupId":"19ec7a85-154a-489e-a191-2ee90d018aa2","EntityName":null,"LastKnownIsCalculatedEntity":false,"LastKnownIsLinkedEntity":false,"LastKnownIsParameter":false,"IsHidden":null,"LastKnownResultTypeName":"table","LoadEnabled":false,"DeleteExistingDataOnLoad":false,"FieldsMetadata":{},"HostProperties":{"MappingEditorProperties":"{}","ServiceFeatureFlag_EnableNewCdstDataflowOrchestration":"True","CdsUploadExecutorKey":"CdsUploader","ServiceFeatureFlag_EnableDataflowImported":"True","StorageId":"CD000000-0000-0000-0000-0000000000CD","EnvironmentId":null},"JsonOutputDestinations":null,"BindToDefaultOutputDestination":null,"JsonIncrementalRefreshSettings":null,"JsonStagingDefinition":null}},"FastCombine":true,"AllowNativeQueries":false,"HostContext":{"Type":"CdsT","Details":{"EnvironmentId":"a9862541-e4e7-ed99-bed0-6dc1e7cf2551"}},"HostProperties":null,"SkipAutomaticTypeAndHeaderDetection":false,"DisableAutoAnonymousConnectionUpsert":false,"AllowedModules":null,"DataflowMetadata":"{\"DataflowType\":\"Cdst\",\"DataflowId\":\"ea29e3ec-0ec0-4a06-b8a8-8508fc7c8b25\",\"OwnerUserId\":\"efb1e53c-de0d-499f-92f4-b32a944e9467\",\"OwnerName\":\"Jan Kostejn\",\"OwnerTenantId\":\"67266d43-8de7-494d-9ed8-3d1bd3b3a764\",\"GatewayObjectId\":null,\"ModelSnapshotUri\":\"\",\"GroupId\":\"a9862541-e4e7-ed99-bed0-6dc1e7cf2551\",\"DataflowState\":\"Active\",\"LastUpdateTime\":\"2025-02-04T12:29:38.7144483+00:00\",\"LastStateChangedTime\":null,\"CreatedTime\":\"2025-02-04T12:29:38.7144483+00:00\",\"ExpiresAfter\":null,\"AllowedModules\":null,\"UseHostConnectionProvider\":false,\"SkipAutomaticTypeAndHeaderDetection\":false,\"EditingSessionId\":null,\"HostInformation\":null,\"HostContext\":{\"Type\":\"CdsT\",\"Details\":{\"EnvironmentId\":\"a9862541-e4e7-ed99-bed0-6dc1e7cf2551\"}},\"HostProperties\":{\"ServiceFeatureFlag_EnableNewCdstDataflowOrchestration\":\"True\",\"CdsUploadExecutorKey\":\"CdsUploader\",\"ServiceFeatureFlag_EnableDataflowImported\":\"True\",\"StorageId\":\"CD000000-0000-0000-0000-0000000000CD\",\"EnvironmentId\":null},\"DisableAutoAnonymousConnectionUpsert\":null,\"RelatedDataflowId\":\"f74224ec-d1ea-4c38-9726-9d04913ab50e\",\"TrustedConnections\":null,\"ConnectionOverrides\":[{\"Path\":\"https://pokeapi.co/api/v2/pokemon\",\"Kind\":\"Web\",\"Provider\":\"PowerApps\",\"EnvironmentName\":\"a9862541-e4e7-ed99-bed0-6dc1e7cf2551\",\"ApiName\":\"webcontents\",\"ConnectionName\":\"a4d942d6029449a49df7136f22d5cbaa\",\"CredentialDetails\":{},\"ConnectionParameters\":{}}]}","Dataflow":"{\"name\":\"INTEGRATION | 1 - Pokemons\",\"ppdf:entityThumbprintVersion\":\"1.0\",\"ppdf:dataflowId\":\"ea29e3ec-0ec0-4a06-b8a8-8508fc7c8b25\",\"ppdf:owner\":{\"tenantId\":\"67266d43-8de7-494d-9ed8-3d1bd3b3a764\",\"userId\":\"efb1e53c-de0d-499f-92f4-b32a944e9467\"},\"ppdf:fastCopy\":false,\"version\":\"1.0\",\"culture\":\"en-US\",\"modifiedTime\":\"2025-02-04T12:29:41.4286797+00:00\",\"ppdf:outputFileFormat\":\"Csv\",\"pbi:mashup\":{\"fastCombine\":true,\"allowNativeQueries\":false,\"queriesMetadata\":{\"_baseUrl\":{\"queryId\":\"5b28a664-9c1d-46af-b60c-9743b529d218\",\"queryName\":\"_baseUrl\",\"queryGroupId\":\"c899add4-255b-4c9a-9d48-d233b6029e26\",\"lastKnownResultTypeName\":\"text\",\"lastKnownIsCalculatedEntity\":false,\"lastKnownIsLinkedEntity\":false,\"lastKnownIsParameter\":false,\"deleteExistingDataOnLoad\":false,\"hostProperties\":{\"MappingEditorProperties\":\"{}\",\"ServiceFeatureFlag_EnableNewCdstDataflowOrchestration\":\"True\",\"CdsUploadExecutorKey\":\"CdsUploader\",\"ServiceFeatureFlag_EnableDataflowImported\":\"True\",\"StorageId\":\"CD000000-0000-0000-0000-0000000000CD\",\"EnvironmentId\":null}},\"e_pokemons-api\":{\"queryId\":\"0fb86dd5-096e-4a2f-9814-61b6b6048368\",\"queryName\":\"e_pokemons-api\",\"queryGroupId\":\"c899add4-255b-4c9a-9d48-d233b6029e26\",\"lastKnownResultTypeName\":\"table\",\"lastKnownIsCalculatedEntity\":false,\"lastKnownIsLinkedEntity\":false,\"lastKnownIsParameter\":false,\"deleteExistingDataOnLoad\":false,\"hostProperties\":{\"MappingEditorProperties\":\"{}\",\"ServiceFeatureFlag_EnableNewCdstDataflowOrchestration\":\"True\",\"CdsUploadExecutorKey\":\"CdsUploader\",\"ServiceFeatureFlag_EnableDataflowImported\":\"True\",\"StorageId\":\"CD000000-0000-0000-0000-0000000000CD\",\"EnvironmentId\":null}},\"udpp25_pokemon\":{\"queryId\":\"44a4bf99-c8bd-430a-af85-a60a23e41c06\",\"queryName\":\"udpp25_pokemon\",\"queryGroupId\":\"d7ddedf8-c3d5-4d9c-b2c0-06f0c6f96ee5\",\"entityName\":\"udpp25_Pokemon\",\"loadEnabled\":true,\"lastKnownResultTypeName\":\"table\",\"lastKnownIsCalculatedEntity\":false,\"lastKnownIsLinkedEntity\":false,\"lastKnownIsParameter\":false,\"deleteExistingDataOnLoad\":true,\"hostProperties\":{\"MappingEditorProperties\":\"{\\\"primaryKeyLogicalName\\\":\\\"udpp25_name\\\"}\",\"ServiceFeatureFlag_EnableNewCdstDataflowOrchestration\":\"True\",\"CdsUploadExecutorKey\":\"CdsUploader\",\"ServiceFeatureFlag_EnableDataflowImported\":\"True\",\"StorageId\":\"CD000000-0000-0000-0000-0000000000CD\",\"EnvironmentId\":null},\"fieldsMetadata\":{\"udpp25_Name\":{\"sourceColumnName\":\"udpp25_Name\",\"destinationFieldType\":\"Memo\"},\"udpp25_Url\":{\"sourceColumnName\":\"udpp25_Url\",\"destinationFieldType\":\"Memo\"}}},\"t_pokemons-api\":{\"queryId\":\"ef1c7404-79d6-4d51-9940-e1d32b7011fe\",\"queryName\":\"t_pokemons-api\",\"queryGroupId\":\"19ec7a85-154a-489e-a191-2ee90d018aa2\",\"lastKnownResultTypeName\":\"table\",\"lastKnownIsCalculatedEntity\":false,\"lastKnownIsLinkedEntity\":false,\"lastKnownIsParameter\":false,\"deleteExistingDataOnLoad\":false,\"hostProperties\":{\"MappingEditorProperties\":\"{}\",\"ServiceFeatureFlag_EnableNewCdstDataflowOrchestration\":\"True\",\"CdsUploadExecutorKey\":\"CdsUploader\",\"ServiceFeatureFlag_EnableDataflowImported\":\"True\",\"StorageId\":\"CD000000-0000-0000-0000-0000000000CD\",\"EnvironmentId\":null}}},\"document\":\"section Section1;\\r\\nshared _baseUrl = let\\n  _baseUrl = \\\"https://pokeapi.co/api/v2/\\\"\\nin\\n  _baseUrl;\\r\\nshared #\\\"e_pokemons-api\\\" = let\\n  Source = Json.Document(Web.Contents(_baseUrl &amp; \\\"pokemon\\\")),\\n  #\\\"Converted to table\\\" = Table.FromRecords({Source}),\\n  #\\\"Expanded results\\\" = Table.ExpandListColumn(#\\\"Converted to table\\\", \\\"results\\\"),\\n  #\\\"Expanded results1\\\" = Table.ExpandRecordColumn(#\\\"Expanded results\\\", \\\"results\\\", {\\\"name\\\", \\\"url\\\"}, {\\\"results.name\\\", \\\"results.url\\\"}),\\n  #\\\"Changed column type\\\" = Table.TransformColumnTypes(#\\\"Expanded results1\\\", {{\\\"count\\\", Int64.Type}, {\\\"next\\\", type text}, {\\\"results.name\\\", type text}, {\\\"results.url\\\", type text}})\\nin\\n  #\\\"Changed column type\\\";\\r\\nshared udpp25_pokemon = let\\n  Source = Table.FromRecords({}),\\n  #\\\"Appended query\\\" = Table.Combine({Source, #\\\"t_pokemons-api\\\"})\\nin\\n  #\\\"Appended query\\\";\\r\\nshared #\\\"t_pokemons-api\\\" = let\\n  Source = #\\\"e_pokemons-api\\\",\\n  #\\\"Choose columns\\\" = Table.SelectColumns(Source, {\\\"results.name\\\", \\\"results.url\\\"}),\\n  #\\\"Renamed columns\\\" = Table.RenameColumns(#\\\"Choose columns\\\", {{\\\"results.name\\\", \\\"udpp25_Name\\\"}, {\\\"results.url\\\", \\\"udpp25_Url\\\"}})\\nin\\n  #\\\"Renamed columns\\\";\\r\\n\"},\"annotations\":[{\"name\":\"pbi:QueryGroups\",\"value\":\"[{\\\"Id\\\":\\\"41902d4e-14d9-423c-bfd9-a3c05086e3a3\\\",\\\"Name\\\":\\\"extract\\\",\\\"Description\\\":\\\"\\\",\\\"ParentId\\\":null,\\\"Order\\\":0},{\\\"Id\\\":\\\"c899add4-255b-4c9a-9d48-d233b6029e26\\\",\\\"Name\\\":\\\"pokemon-api\\\",\\\"Description\\\":\\\"\\\",\\\"ParentId\\\":\\\"41902d4e-14d9-423c-bfd9-a3c05086e3a3\\\",\\\"Order\\\":0},{\\\"Id\\\":\\\"19ec7a85-154a-489e-a191-2ee90d018aa2\\\",\\\"Name\\\":\\\"transform\\\",\\\"Description\\\":\\\"\\\",\\\"ParentId\\\":null,\\\"Order\\\":1},{\\\"Id\\\":\\\"d7ddedf8-c3d5-4d9c-b2c0-06f0c6f96ee5\\\",\\\"Name\\\":\\\"load\\\",\\\"Description\\\":\\\"\\\",\\\"ParentId\\\":null,\\\"Order\\\":2}]\"}],\"entities\":[{\"$type\":\"LocalEntity\",\"name\":\"udpp25_pokemon\",\"description\":\"\",\"pbi:refreshPolicy\":{\"$type\":\"FullRefreshPolicy\",\"location\":\"udpp25_pokemon.csv\"},\"annotations\":[{\"name\":\"ppdf:entityKeys\",\"value\":\"[]\"}],\"attributes\":[{\"name\":\"udpp25_Name\",\"dataType\":\"string\"},{\"name\":\"udpp25_Url\",\"dataType\":\"string\"}]}]}"}</msdyn_mashupsettings>
      <msdyn_name>INTEGRATION | 1 - Pokemons</msdyn_name>
      <msdyn_originaldataflowid>ea29e3ec-0ec0-4a06-b8a8-8508fc7c8b25</msdyn_originaldataflowid>
      <statecode>0</statecode>
      <statuscode>1</statuscode>
    </msdyn_dataflow>
  </msdyn_dataflows>
  <Languages>
    <Language>1033</Language>
  </Languages>
</ImportExportXml>